[
  {
    "variation": "default",
    "version": "sktwi1xtmkfgx8626",
    "items": [
      {}
    ],
    "primary": {
      "title": [
        {
          "type": "heading2",
          "text": "Slope",
          "spans": []
        }
      ],
      "subtitle": [
        {
          "type": "heading2",
          "text": "Previous",
          "spans": []
        }
      ],
      "name": "whispered",
      "email": "eaten",
      "message": "fur"
    },
    "slice_type": "contact"
  },
  {
    "variation": "cotizarForm",
    "version": "sktwi1xtmkfgx8626",
    "items": [
      {}
    ],
    "primary": {
      "subtitle": [
        {
          "type": "heading2",
          "text": "Tonight",
          "spans": []
        }
      ],
      "name": "seen",
      "email": "leader"
    },
    "slice_type": "contact"
  },
  {
    "variation": "enroll",
    "version": "sktwi1xtmkfgx8626",
    "items": [
      {}
    ],
    "primary": {
      "title": [
        {
          "type": "heading2",
          "text": "Movement",
          "spans": []
        }
      ],
      "subtitle": [
        {
          "type": "heading2",
          "text": "Coach",
          "spans": []
        }
      ],
      "name": "twice",
      "birthday": "work",
      "address": "record",
      "phone": "control",
      "email": "rhyme",
      "profession": "valley",
      "studyinthearea": "respect",
      "medicalhistory": "log",
      "emergencycontact": "shout"
    },
    "slice_type": "contact"
  }
]